scientist/__init__.py
scientist/experiment.py
scientist/settings.py
scientist/utils.py
scientist-0.1.0.dist-info/DESCRIPTION.rst
scientist-0.1.0.dist-info/METADATA
scientist-0.1.0.dist-info/metadata.json
scientist-0.1.0.dist-info/RECORD
scientist-0.1.0.dist-info/top_level.txt
scientist-0.1.0.dist-info/WHEEL
