Metadata-Version: 2.0
Name: scientist
Version: 0.1.0
Summary: Scientist: Take a scalpel to your critical paths
Home-page: http://www.github.com/staticshock/scientist.py
Author: Anton Backer
Author-email: olegov@gmail.com
License: MIT
Platform: UNKNOWN
Classifier: Development Status :: 4 - Beta
Classifier: Intended Audience :: Developers
Classifier: Natural Language :: English
Classifier: License :: OSI Approved :: MIT License
